villq/__init__.py
villq/fade.py
villq-1.1.0.dist-info/METADATA
villq-1.1.0.dist-info/WHEEL
villq-1.1.0.dist-info/top_level.txt
villq-1.1.0.dist-info/RECORD
