Metadata-Version: 2.1
Name: villq
Version: 1.1.0
Summary: This Module Creates a Purple Fade Effect on ASCII Art and Text.
Home-page: https://github.com/vChimera/anvilly
Author: Anvil
Author-email: _@chimera.rip
Classifier: Programming Language :: Python :: 3
Classifier: License :: OSI Approved :: MIT License
Classifier: Operating System :: OS Independent
Requires-Python: >=3.6
